coloco-0.4.7.dist-info/METADATA
coloco-0.4.7.dist-info/WHEEL
coloco-0.4.7.dist-info/entry_points.txt
coloco-0.4.7.dist-info/licenses/LICENSE
coloco/__init__.py
coloco/__main__.py
coloco/api.py
coloco/app.py
coloco/cli/api.py
coloco/cli/build.py
coloco/cli/createapp.py
coloco/cli/db.py
coloco/cli/dev.py
coloco/cli/node.py
coloco/cli/package.py
coloco/cli/serve.py
coloco/codegen.py
coloco/config.py
coloco/db.py
coloco/dependencies.py
coloco/exceptions.py
coloco/lifespan.py
coloco/static.py
coloco/templates/docker/.dockerignore-tpl
coloco/templates/docker/Dockerfile-tpl
coloco/templates/docker/docker-compose.yml-tpl
coloco/templates/standard/+app/404.svelte-tpl
coloco/templates/standard/+app/app.css-tpl
coloco/templates/standard/+app/app.svelte-tpl
coloco/templates/standard/+app/index.html-tpl
coloco/templates/standard/+app/index.svelte-tpl
coloco/templates/standard/+app/main.ts-tpl
coloco/templates/standard/+node/openapi-ts.config.ts-tpl
coloco/templates/standard/+node/package.json-tpl
coloco/templates/standard/+node/svelte.config.js-tpl
coloco/templates/standard/+node/tsconfig.json-tpl
coloco/templates/standard/+node/vite-env.d.ts-tpl
coloco/templates/standard/+node/vite.config.ts-tpl
coloco/templates/standard/.gitignore-tpl
coloco/templates/standard/README.md-tpl
coloco/templates/standard/example/api.py-tpl
coloco/templates/standard/example/index.svelte-tpl
coloco/templates/standard/main.py-tpl
coloco/templates/standard/pyproject.toml-tpl
coloco/templates/standard/tsconfig.json-tpl
coloco-0.4.7.dist-info/RECORD
