Metadata-Version: 2.1
Name: coloco
Version: 0.4.7
Summary: A kit for creating FastAPI + Svelte applications
Author-Email: Channel Cat <channelcat@gmail.com>
License: MIT
Requires-Python: >=3.12
Requires-Dist: cyclopts>=3.18.0
Requires-Dist: fastapi>=0.115.0
Requires-Dist: PyJWT>=2.10.1
Requires-Dist: tortoise-orm[asyncpg]>=0.24.0
Requires-Dist: tortoise-pathway==0.2.0
Requires-Dist: type-less>=0.1.16
Requires-Dist: uvicorn>=0.31.0
